<?xml version="1.0" encoding="utf-8"?>
<Application xmlns:xsd="http://www.w3.org/2001/XMLSchema" xmlns:xsi="http://www.w3.org/2001/XMLSchema-instance" Name="fabric:/TravelPlanner" xmlns="http://schemas.microsoft.com/2011/01/fabric">
  <Parameters>
    <Parameter Name="Identity_DefaultConnection" Value="Server=localhost;Database=TravelPlannerDb;Trusted_Connection=True;TrustServerCertificate=True;" />
    <Parameter Name="Identity_JwtSecret" Value="CHANGE_ME_LOCAL_JWT_SECRET_32_CHARS_MINIMUM" />
    <Parameter Name="Identity_JwtIssuer" Value="TravelPlanner.Local" />
    <Parameter Name="Identity_JwtAudience" Value="TravelPlanner.Frontend" />
    <Parameter Name="Identity_JwtExpirationMinutes" Value="60" />
    <Parameter Name="ApiGateway_JwtSecret" Value="CHANGE_ME_LOCAL_JWT_SECRET_32_CHARS_MINIMUM" />
    <Parameter Name="ApiGateway_JwtIssuer" Value="TravelPlanner.Local" />
    <Parameter Name="ApiGateway_JwtAudience" Value="TravelPlanner.Frontend" />
    <Parameter Name="ApiGateway_AllowDevUserHeaderFallback" Value="false" />
    <Parameter Name="TripPlanning_DefaultConnection" Value="Server=localhost;Database=TravelPlannerDb;Trusted_Connection=True;TrustServerCertificate=True;" />
    <Parameter Name="Budget_DefaultConnection" Value="Server=localhost;Database=TravelPlannerDb;Trusted_Connection=True;TrustServerCertificate=True;" />
    <Parameter Name="Sharing_DefaultConnection" Value="Server=localhost;Database=TravelPlannerDb;Trusted_Connection=True;TrustServerCertificate=True;" />
  </Parameters>
</Application>
